[

    { "id": "1",
      "titulo": "Kia Rio 5 como nuevo",
      "marca":"kia",
      "modelo": "rio 5",
      "kilometraje": 20000,
      "ano": 2015,
      "duenos": 2,
      "combustible":"bencina",
      "transmision": "manual",
      "precio": 7000000,
      "estado": "usado",
      "detalles": "Vehiculo excelnte estado, nunca chocado. Mantenciones al dia en la consecionaria",
      "imagen":"https://chileautos.pxcrush.net/car/dealer/3csu1l7cmn4f0uhfbeyr5xa3a.jpg?pxc_method=limitfill&pxc_bgtype=self&pxc_size=900%2c600"
    },
    { 
      "id": "2",
      "titulo": "Espectacular Nissan Navara 2012",
      "marca":"nissan",
      "modelo": "navara",
      "kilometraje": 130000,
      "ano": 2012,
      "duenos": 1,
      "combustible":"diesel",
      "transmision": "manual",
      "precio": 11500000,
      "estado": "usado",
      "detalles": "camioneta como nueva, no usada para trabajos pesados.",
      "imagen":"https://chileautos.pxcrush.net/chileautos/cars/private/b67e8a57kpaenx2lmm8m0d6ok.jpg?pxc_method=fit&pxc_size=1795%2c1195"
    },
    { "id":"3",
      "titulo": "Hyundai I20 2018",
      "marca":"hyundai",
      "modelo": "i20",
      "kilometraje": 78000,
      "ano": 2018,
      "duenos": 2,
      "combustible":"bencina",
      "transmision": "automatico",
      "precio": 12000000,
      "estado": "usado",
      "detalles": "Mantenciones al dia, usado en ciudad. No viajes largos",
      "imagen":"https://chileautos.pxcrush.net/cars/dealer/e6ysa8bcx1j2mdu42669cds55.jpg?pxc_method=fit&pxc_size=1795%2c1195"
    },
    { "id":"4",
      "titulo": "Ford Edge 2020",
      "marca":"ford",
      "modelo": "edge",
      "kilometraje": 53000,
      "ano": 2020,
      "duenos": 1,
      "combustible":"bencina",
      "transmision": "automatico",
      "precio": 26000000,
      "estado": "usado",
      "detalles": "Mantenciones al dia en concesionaria, uso fin de semanas.",
      "imagen":"https://chileautos.pxcrush.net/cars/dealer/5711uiofzl7mjai4eooi206lb.jpg?pxc_method=fit&pxc_size=1795%2c1195"
    },
    { "id": "5",
      "titulo": "Subaru Forester 2019",
      "marca":"subaru",
      "modelo": "forester",
      "kilometraje": 67000,
      "ano": 2019,
      "duenos": 2,
      "combustible":"bencina",
      "transmision": "manual",
      "precio": 18850000,
      "estado": "usado",
      "detalles": "Mantenciones al dia en concesionaria.",
      "imagen":"https://chileautos.pxcrush.net/cars/dealer/1dgl2du6xcyrf0puyx068bfpd.jpg?pxc_method=fit&pxc_size=1795%2c1195"
    },
    { "id": "6",
      "titulo": "Volkswagen gol 2023",
      "marca":"volkswagen",
      "modelo": "gol",
      "kilometraje": 50,
      "ano": 2023,
      "duenos": 0,
      "combustible":"bencina",
      "transmision": "manual",
      "precio": 11990000,
      "estado": "nuevo",
      "detalles": "Puedes llevar a credito.",
      "imagen":"https://chileautos.pxcrush.net/car/dealer/6wi29y65ti5tmud7f5ntgthgt.jpg?pxc_method=fit&pxc_size=1795%2c1195"
    },
    { "id": "7",
      "titulo": "Peugeot 3008",
      "marca":"peugeot",
      "modelo": "blueHDI",
      "kilometraje": 74000,
      "ano": 2018,
      "duenos": 2,
      "combustible":"diesel",
      "transmision": "automatico",
      "precio": 18000000,
      "estado": "usado",
      "detalles": "se vende por renovacion, sin detallles.",
      "imagen":"https://chileautos.pxcrush.net/cars/dealer/9nryd24ssby5ojmmopx6no047.jpg?pxc_method=fit&pxc_size=1795%2c1195"
    },
    { "id": "8",
      "titulo": "Opel Crossland",
      "marca":"opel",
      "modelo": "crossland",
      "kilometraje": 10,
      "ano": 2023,
      "duenos": 0,
      "combustible":"diesel",
      "transmision": "manual",
      "precio": 20990000,
      "estado": "nuevo",
      "detalles": "Puedes llevar a credito.",
      "imagen":"https://chileautos.pxcrush.net/cars/dealer/248r671dbetkuiarbhgvx9vmy.jpg?pxc_method=limitfill&pxc_bgtype=self&pxc_size=900%2c600"
    }
  
]











